AIserver/__init__.py
AIserver/chartAI.py
AIserver/client.py
AIserver/server.py
AIserver/test.py
AIserver-0.0.9.dist-info/LICENSE.txt
AIserver-0.0.9.dist-info/METADATA
AIserver-0.0.9.dist-info/WHEEL
AIserver-0.0.9.dist-info/top_level.txt
AIserver-0.0.9.dist-info/RECORD
