Metadata-Version: 2.1
Name: AIserver
Version: 0.0.9
Summary: This is a packege for AI 
Home-page: UNKNOWN
Author: 快乐风男
Author-email: UNKNOWN
License: UNKNOWN
Platform: UNKNOWN
Classifier: Programming Language :: Python :: 3
Classifier: License :: OSI Approved :: MIT License
Classifier: Operating System :: OS Independent
